swh/shard/__init__.py
swh/shard/_shard.cpython-312-x86_64-linux-musl.so
swh/shard/cli.py
swh/shard/py.typed
swh/shard/tests/__init__.py
swh/shard/tests/test_cli.py
swh/shard/tests/test_shard.py
swh_shard.libs/libgcc_s-0cd532bd.so.1
swh_shard.libs/libstdc++-5d72f927.so.6.0.33
swh_shard-2.2.0.dist-info/METADATA
swh_shard-2.2.0.dist-info/WHEEL
swh_shard-2.2.0.dist-info/entry_points.txt
swh_shard-2.2.0.dist-info/RECORD
swh_shard-2.2.0.dist-info/licenses/AUTHORS
swh_shard-2.2.0.dist-info/licenses/LICENSE
