Metadata-Version: 2.1
Name: swh.shard
Version: 2.2.0
Summary: Software Heritage Shard File Format
Author-Email: Software Heritage developers <swh-devel@inria.fr>
Classifier: Programming Language :: Python :: 3
Classifier: Intended Audience :: Developers
Classifier: License :: OSI Approved :: GNU General Public License v3 (GPLv3)
Classifier: Operating System :: OS Independent
Classifier: Development Status :: 3 - Alpha
Classifier: Programming Language :: Python :: Implementation :: CPython
Classifier: Programming Language :: Python :: Implementation :: PyPy
Project-URL: Homepage, https://gitlab.softwareheritage.org/swh/devel/swh-shard
Project-URL: Bug Reports, https://gitlab.softwareheritage.org/swh/devel/swh-shard/-/issues
Project-URL: Funding, https://www.softwareheritage.org/donate
Project-URL: Documentation, https://docs.softwareheritage.org/devel/swh-shard/
Project-URL: Source, https://gitlab.softwareheritage.org/swh/devel/swh-shard.git
Requires-Python: >=3.10
Requires-Dist: click>=8.2.0
Provides-Extra: testing
Requires-Dist: pytest>=8.1; extra == "testing"
Requires-Dist: pytest-mock; extra == "testing"
